hadron/__init__.py
hadron-0.0.1.dist-info/LICENSE.md
hadron-0.0.1.dist-info/METADATA
hadron-0.0.1.dist-info/WHEEL
hadron-0.0.1.dist-info/top_level.txt
hadron-0.0.1.dist-info/RECORD
